RBHC/Clustering.py
RBHC/__init__.py
RBHC-1.0.1.dist-info/LICENSE
RBHC-1.0.1.dist-info/METADATA
RBHC-1.0.1.dist-info/WHEEL
RBHC-1.0.1.dist-info/top_level.txt
RBHC-1.0.1.dist-info/RECORD
