Metadata-Version: 2.1
Name: RBHC
Version: 1.0.1
Summary: RBHC
Home-page: https://github.com/intuit/RBHC
Author: Ashwith Atluri
Author-email: ashwithatluri@gmail.com
License: UNKNOWN
Platform: UNKNOWN
Requires-Dist: pandas
Requires-Dist: scikit-learn
Requires-Dist: numpy
Requires-Dist: matplotlib
Requires-Dist: jupyter
